aacgm2/__init__.py
aacgm2/__main__.py
aacgm2/_aacgmv2.so
aacgm2/igrf13coeffs.txt
aacgm2/magmodel_1590-2020.txt
aacgm2/wrapper.py
aacgm2/aacgm_coeffs/aacgm_coeffs-13-1590.asc
aacgm2/aacgm_coeffs/aacgm_coeffs-13-1595.asc
aacgm2/aacgm_coeffs/aacgm_coeffs-13-1600.asc
aacgm2/aacgm_coeffs/aacgm_coeffs-13-1605.asc
aacgm2/aacgm_coeffs/aacgm_coeffs-13-1610.asc
aacgm2/aacgm_coeffs/aacgm_coeffs-13-1615.asc
aacgm2/aacgm_coeffs/aacgm_coeffs-13-1620.asc
aacgm2/aacgm_coeffs/aacgm_coeffs-13-1625.asc
aacgm2/aacgm_coeffs/aacgm_coeffs-13-1630.asc
aacgm2/aacgm_coeffs/aacgm_coeffs-13-1635.asc
aacgm2/aacgm_coeffs/aacgm_coeffs-13-1640.asc
aacgm2/aacgm_coeffs/aacgm_coeffs-13-1645.asc
aacgm2/aacgm_coeffs/aacgm_coeffs-13-1650.asc
aacgm2/aacgm_coeffs/aacgm_coeffs-13-1655.asc
aacgm2/aacgm_coeffs/aacgm_coeffs-13-1660.asc
aacgm2/aacgm_coeffs/aacgm_coeffs-13-1665.asc
aacgm2/aacgm_coeffs/aacgm_coeffs-13-1670.asc
aacgm2/aacgm_coeffs/aacgm_coeffs-13-1675.asc
aacgm2/aacgm_coeffs/aacgm_coeffs-13-1680.asc
aacgm2/aacgm_coeffs/aacgm_coeffs-13-1685.asc
aacgm2/aacgm_coeffs/aacgm_coeffs-13-1690.asc
aacgm2/aacgm_coeffs/aacgm_coeffs-13-1695.asc
aacgm2/aacgm_coeffs/aacgm_coeffs-13-1700.asc
aacgm2/aacgm_coeffs/aacgm_coeffs-13-1705.asc
aacgm2/aacgm_coeffs/aacgm_coeffs-13-1710.asc
aacgm2/aacgm_coeffs/aacgm_coeffs-13-1715.asc
aacgm2/aacgm_coeffs/aacgm_coeffs-13-1720.asc
aacgm2/aacgm_coeffs/aacgm_coeffs-13-1725.asc
aacgm2/aacgm_coeffs/aacgm_coeffs-13-1730.asc
aacgm2/aacgm_coeffs/aacgm_coeffs-13-1735.asc
aacgm2/aacgm_coeffs/aacgm_coeffs-13-1740.asc
aacgm2/aacgm_coeffs/aacgm_coeffs-13-1745.asc
aacgm2/aacgm_coeffs/aacgm_coeffs-13-1750.asc
aacgm2/aacgm_coeffs/aacgm_coeffs-13-1755.asc
aacgm2/aacgm_coeffs/aacgm_coeffs-13-1760.asc
aacgm2/aacgm_coeffs/aacgm_coeffs-13-1765.asc
aacgm2/aacgm_coeffs/aacgm_coeffs-13-1770.asc
aacgm2/aacgm_coeffs/aacgm_coeffs-13-1775.asc
aacgm2/aacgm_coeffs/aacgm_coeffs-13-1780.asc
aacgm2/aacgm_coeffs/aacgm_coeffs-13-1785.asc
aacgm2/aacgm_coeffs/aacgm_coeffs-13-1790.asc
aacgm2-2.6.0.dist-info/AUTHORS.rst
aacgm2-2.6.0.dist-info/LICENSE
aacgm2-2.6.0.dist-info/METADATA
aacgm2-2.6.0.dist-info/WHEEL
aacgm2-2.6.0.dist-info/entry_points.txt
aacgm2-2.6.0.dist-info/top_level.txt
aacgm2-2.6.0.dist-info/RECORD
