Metadata-Version: 2.1
Name: aacgm2
Version: 2.6.0
Summary: A Python wrapper for AACGM-v2 magnetic coordinates
Home-page: https://github.com/st-bender/aacgmv2
Author: Angeline G. Burrell, Christer van der Meeren
Author-email: angeline.burrell@nrl.navy.mil
Maintainer: Stefan Bender
Maintainer-email: stefan.bender@ntnu.no
License: MIT
Keywords: aacgm,aacgm-v2,aacgmv2,magnetic coordinates,altitude adjusted corrected geomagnetic coordinates,mlt,magnetic local time,conversion,converting
Platform: UNKNOWN
Classifier: Development Status :: 5 - Production/Stable
Classifier: Intended Audience :: Science/Research
Classifier: License :: OSI Approved :: MIT License
Classifier: Operating System :: Unix
Classifier: Operating System :: POSIX
Classifier: Operating System :: Microsoft :: Windows
Classifier: Programming Language :: Python
Classifier: Programming Language :: Python :: 2
Classifier: Programming Language :: Python :: 2.7
Classifier: Programming Language :: Python :: 3
Classifier: Programming Language :: Python :: 3.4
Classifier: Programming Language :: Python :: 3.5
Classifier: Programming Language :: Python :: 3.6
Classifier: Programming Language :: Python :: 3.7
Classifier: Programming Language :: Python :: 3.8
Classifier: Programming Language :: Python :: Implementation :: CPython
Classifier: Topic :: Scientific/Engineering :: Physics
Classifier: Topic :: Utilities
